README.md
setup.cfg
setup.py
aiochorm/__init__.py
aiochorm/database.py
aiochorm/engines.py
aiochorm/fields.py
aiochorm/migrations.py
aiochorm/models.py
aiochorm/query.py
aiochorm/system_models.py
aiochorm/utils.py
aiochorm.egg-info/PKG-INFO
aiochorm.egg-info/SOURCES.txt
aiochorm.egg-info/dependency_links.txt
aiochorm.egg-info/requires.txt
aiochorm.egg-info/top_level.txt